openbb_us_eia/__init__.py
openbb_us_eia/models/__init__.py
openbb_us_eia/models/petroleum_status_report.py
openbb_us_eia/models/short_term_energy_outlook.py
openbb_us_eia/utils/__init__.py
openbb_us_eia/utils/constants.py
openbb_us_eia/utils/helpers.py
openbb_us_eia/utils/py.typed
openbb_us_eia/utils/total_energy_map.json
openbb_us_eia-1.1.1.dist-info/METADATA
openbb_us_eia-1.1.1.dist-info/WHEEL
openbb_us_eia-1.1.1.dist-info/entry_points.txt
openbb_us_eia-1.1.1.dist-info/RECORD
