Metadata-Version: 2.3
Name: openbb-us-eia
Version: 1.1.1
Summary: The U.S. Energy Information Administration is committed to its free and open data by making it available through an Application Programming Interface (API) and its open data tools. See https://www.eia.gov/opendata/ for more information.
License: AGPL-3.0-only
Author: OpenBB Team
Author-email: hello@openbb.co
Requires-Python: >=3.9.21,<3.13
Classifier: License :: OSI Approved :: GNU Affero General Public License v3
Classifier: Programming Language :: Python :: 3
Classifier: Programming Language :: Python :: 3.10
Classifier: Programming Language :: Python :: 3.11
Classifier: Programming Language :: Python :: 3.12
Requires-Dist: async-lru (>=2.0.4,<3.0.0)
Requires-Dist: openbb-core (>=1.4.6,<2.0.0)
Requires-Dist: openpyxl (>=3.1.5,<4.0.0)
Requires-Dist: xlrd (>=2.0.1,<3.0.0)
